zigpy_xbee/__init__.py
zigpy_xbee/api.py
zigpy_xbee/config.py
zigpy_xbee/exceptions.py
zigpy_xbee/types.py
zigpy_xbee/uart.py
zigpy_xbee/zigbee/__init__.py
zigpy_xbee/zigbee/application.py
zigpy_xbee-0.21.0.dist-info/COPYING
zigpy_xbee-0.21.0.dist-info/LICENSE
zigpy_xbee-0.21.0.dist-info/METADATA
zigpy_xbee-0.21.0.dist-info/WHEEL
zigpy_xbee-0.21.0.dist-info/top_level.txt
zigpy_xbee-0.21.0.dist-info/RECORD
