Metadata-Version: 2.1
Name: zigpy-xbee
Version: 0.21.0
Summary: A library which communicates with XBee radios for zigpy
Author-email: Russell Cloran <rcloran@gmail.com>
License: GPL-3.0
Project-URL: repository, https://github.com/zigpy/zigpy-xbee
Requires-Python: >=3.8
License-File: LICENSE
License-File: COPYING
Requires-Dist: zigpy>=0.70.0
Provides-Extra: testing
Requires-Dist: pytest>=7.1.2; extra == "testing"
Requires-Dist: asynctest>=0.13.0; extra == "testing"
Requires-Dist: pytest-asyncio>=0.19.0; extra == "testing"
